nasalgeom/__init__.py
nasalgeom/denoise.py
nasalgeom/dicom_io.py
nasalgeom/enhance.py
nasalgeom/helpers.py
nasalgeom/mar.py
nasalgeom/quality.py
nasalgeom/rhinometry.py
nasalgeom/segmentation.py
nasalgeom/stlfix.py
nasalgeom/surface.py
nasalgeom-1.0.0.data/scripts/nasal-geom
nasalgeom-1.0.0.dist-info/DESCRIPTION.rst
nasalgeom-1.0.0.dist-info/METADATA
nasalgeom-1.0.0.dist-info/RECORD
nasalgeom-1.0.0.dist-info/WHEEL
nasalgeom-1.0.0.dist-info/metadata.json
nasalgeom-1.0.0.dist-info/top_level.txt
